quickey_python_sdk/__init__.py
quickey_python_sdk/app.py
quickey_python_sdk/auth.py
quickey_python_sdk/config.py
quickey_python_sdk/sdk.py
quickey_python_sdk-1.0.13.dist-info/LICENSE
quickey_python_sdk-1.0.13.dist-info/METADATA
quickey_python_sdk-1.0.13.dist-info/WHEEL
quickey_python_sdk-1.0.13.dist-info/top_level.txt
quickey_python_sdk-1.0.13.dist-info/RECORD
