Metadata-Version: 2.1
Name: quickey-python-sdk
Version: 1.0.13
Summary: A Login Management System for Application
Home-page: https://github.com/efrizal-analisa/quickey_python_sdk
Author: quickey team
Author-email: efrizal@analisa.io
License: UNKNOWN
Platform: UNKNOWN
Classifier: Programming Language :: Python :: 3
Classifier: License :: OSI Approved :: MIT License
Classifier: Operating System :: OS Independent
